ckanext_toolbelt-0.6.10-py3.10-nspkg.pth
ckanext/toolbelt/__init__.py
ckanext/toolbelt/decorators.py
ckanext/toolbelt/cli/__init__.py
ckanext/toolbelt/cli/_shared.py
ckanext/toolbelt/cli/dev.py
ckanext/toolbelt/cli/make.py
ckanext/toolbelt/cli/make_ckanext.py
ckanext/toolbelt/cli/make_config.py
ckanext/toolbelt/cli/make_gh_action.py
ckanext/toolbelt/cli/make_readme.py
ckanext/toolbelt/cli/make_template.py
ckanext/toolbelt/cli/ckan/__init__.py
ckanext/toolbelt/cli/ckan/db.py
ckanext/toolbelt/cli/ckan/search_index.py
ckanext/toolbelt/cli/cookiecutter/extended/cookiecutter.json
ckanext/toolbelt/cli/cookiecutter/extended/{{ cookiecutter.project }}/.editorconfig
ckanext/toolbelt/cli/cookiecutter/extended/{{ cookiecutter.project }}/.gitignore
ckanext/toolbelt/cli/cookiecutter/extended/{{ cookiecutter.project }}/.gitleaksignore
ckanext/toolbelt/cli/cookiecutter/extended/{{ cookiecutter.project }}/.node-version
ckanext/toolbelt/cli/cookiecutter/extended/{{ cookiecutter.project }}/.nvmrc
ckanext/toolbelt/cli/cookiecutter/extended/{{ cookiecutter.project }}/.pre-commit-config.yaml
ckanext/toolbelt/cli/cookiecutter/extended/{{ cookiecutter.project }}/LICENSE
ckanext/toolbelt/cli/cookiecutter/extended/{{ cookiecutter.project }}/MANIFEST.in
ckanext/toolbelt/cli/cookiecutter/extended/{{ cookiecutter.project }}/Makefile
ckanext/toolbelt/cli/cookiecutter/extended/{{ cookiecutter.project }}/README.md
ckanext/toolbelt/cli/cookiecutter/extended/{{ cookiecutter.project }}/cliff.toml
ckanext/toolbelt/cli/cookiecutter/extended/{{ cookiecutter.project }}/cypress.config.ts
ckanext/toolbelt/cli/cookiecutter/extended/{{ cookiecutter.project }}/gulpfile.js
ckanext/toolbelt/cli/cookiecutter/extended/{{ cookiecutter.project }}/mkdocs.yml
ckanext/toolbelt/cli/cookiecutter/extended/{{ cookiecutter.project }}/package-lock.json
ckanext/toolbelt/cli/cookiecutter/extended/{{ cookiecutter.project }}/package.json
ckanext/toolbelt/cli/cookiecutter/extended/{{ cookiecutter.project }}/pyproject.toml
ckanext_toolbelt-0.6.10.dist-info/METADATA
ckanext_toolbelt-0.6.10.dist-info/WHEEL
ckanext_toolbelt-0.6.10.dist-info/entry_points.txt
ckanext_toolbelt-0.6.10.dist-info/namespace_packages.txt
ckanext_toolbelt-0.6.10.dist-info/top_level.txt
ckanext_toolbelt-0.6.10.dist-info/RECORD
