Metadata-Version: 2.4
Name: ckanext-toolbelt
Version: 0.6.10
Author-email: DataShades <datashades@linkdigital.com.au>, Sergey Motornyuk <sergey.motornyuk@linkdigital.com.au>
Maintainer-email: DataShades <datashades@linkdigital.com.au>
License: AGPL
Project-URL: Homepage, https://github.com/DataShades/ckanext-toolbelt
Keywords: CKAN
Requires-Python: >=3.8
Requires-Dist: click
Requires-Dist: aiosmtpd
Requires-Dist: typing_extensions
Requires-Dist: gitpython
Requires-Dist: cookiecutter
Provides-Extra: flask-sqlalchemy
Requires-Dist: flask-sqlalchemy~=2.5; extra == "flask-sqlalchemy"
Provides-Extra: test
Requires-Dist: pytest-ckan; extra == "test"
Requires-Dist: pytest-mock; extra == "test"
